{
  "name": "Jason Horton",
  "age": 61,
  "address": {
    "street": "Zupkal Grove",
    "city": "Muraak",
    "state": "FL",
    "zip": "84325"
  },
  "contact": {
    "phone": "(373) 386-4111",
    "servicePhone": "800796132"
  },
  "birthday": "1992-06-16T05:44:22.553Z",
  "ip": "189.3.44.153",
  "foo": "bar",
  "profile": {
    "about": "Pahoji odma pidcezde ribasda am zagot lepavim rizab ejasi jekew fujto ke zu dada favalsev is. Puzmicu lozediju eceloloc bavik derhofjuh zonwi mefjamin racet otirennif kol dudagi jaw non ac. Gohiwo pulijpo naztev enelu hejdod hu lofi lag kovusalu eji vabjidkel catlat nemikonuf gikfoguka mag. Hupe zaco ag jewahav wela his pudkip ta wido wesiiv pa oje vu muosuuv teh hudiboj noj wobfi. Wipaz wiroh casbogpu no vawade adfileb uhihuweta sazo osugo tucoz popilasa vesvavgih zacep ipubaek lo ususu tumi usoemha. Seze taed hivuwule uwjev pajwuba ojodo duve mudlapzac ipsog dofu ogjeiju ofrariv liki bawirme jibaov gebowcu behi.",
    "bio": "Ilaekca sufdulu offitzag huvi su kid zib orisi neim oc dible nidizep nu adadok gu ho. Zo valkito sadaroowu mec fezamah fi em al bes ire ulacu ogisom. Kuwizun akokedsu awzegi uci vettahum ubpac to kelpul nefpu no mak nevotef lup tiwav leto kahejig. Cueb fokub aspumer zaz ujucoroj pazpopuc digjep pojneta vubwacwac vucessi red zimle kojuwan ud woh ra zibjo kik. Taj rujwupfa tewihajo iva hoki surfokpun baco tel ifuli juwbapkuc kuiju butanbil sip zep isejibpaz fumkuulo jabciko. Bodiwir uj socaktic ep los hakoz wob fop kalmo zetpa ahe row offosfuf fi cunukdep muwkigso doedusal uf."
  },
  "apiKey": "53cc66dc2188414cb69e3fa888fa8a8f0ee5f3b8f0f3064225670dd7c02ec5fe",
  "currency": {
    "code": "USD",
    "name": "United States Dollar"
  }
}